classeval/ROC.py
classeval/__init__.py
classeval/classeval.py
classeval/confmatrix.py
classeval/examples.py
classeval/data/__init__.py
classeval-0.2.2.dist-info/LICENSE
classeval-0.2.2.dist-info/METADATA
classeval-0.2.2.dist-info/WHEEL
classeval-0.2.2.dist-info/top_level.txt
classeval-0.2.2.dist-info/RECORD
