Metadata-Version: 2.1
Name: classeval
Version: 0.2.2
Summary: Python package classeval
Home-page: https://erdogant.github.io/classeval/
Download-URL: https://github.com/erdogant/classeval/archive/0.2.2.tar.gz
Author: Erdogan Taskesen
Author-email: erdogant@gmail.com
Classifier: Programming Language :: Python :: 3
Classifier: License :: OSI Approved :: MIT License
Classifier: Operating System :: OS Independent
Requires-Python: >=3
License-File: LICENSE
Requires-Dist: matplotlib
Requires-Dist: numpy
Requires-Dist: funcsigs
Requires-Dist: scikit-learn
Requires-Dist: colourmap
